[
  {
    "slug": "beste-friteuse-2026",
    "topic_nl": "de beste friteuses (hetelucht én olie) voor thuisgebruik",
    "category": "keuken",
    "audience": "gezinnen en thuiskoks die friet, snacks en zelfgemaakte gerechten willen frituren",
    "product_ideas": "Philips Premium Airfryer XXL, Princess Classic Friteuse, Tefal Oleoclean Pro, Inventum Professionele Friteuse, Domo Frituurpan"
  },
  {
    "slug": "beste-senseo-koffiezetapparaat-2026",
    "topic_nl": "de beste Senseo en pad-koffiezetapparaten voor snelle koffie",
    "category": "keuken",
    "audience": "Nederlandse koffiedrinkers die snel en makkelijk 1-2 kopjes willen zetten",
    "product_ideas": "Philips Senseo Original, Philips Senseo Switch, Melitta Purista, De'Longhi Nespresso, Krups Nespresso"
  },
  {
    "slug": "beste-slowcooker-2026",
    "topic_nl": "de beste slowcookers voor maaltijdvoorbereiding en stoofgerechten",
    "category": "keuken",
    "audience": "drukke huishoudens en meal-preppers die 's ochtends willen voorbereiden en 's avonds willen eten",
    "product_ideas": "Crock-Pot klassiek, Instant Pot Duo, Russell Hobbs, Tefal Cook4Me, Ninja Foodi"
  },
  {
    "slug": "beste-wasmachine-2026",
    "topic_nl": "de beste wasmachines voor gezinnen, energiezuinig en betrouwbaar",
    "category": "huishoudelijk",
    "audience": "Nederlandse huishoudens die een betrouwbare, energiezuinige wasmachine zoeken voor dagelijks gebruik",
    "product_ideas": "Miele W1, Bosch Serie 8, Siemens iQ500, Samsung EcoBubble, LG Direct Drive, AEG ProTex"
  },
  {
    "slug": "beste-wasdroger-2026",
    "topic_nl": "de beste wasdrogers: warmtepomp, condens en energiezuinig",
    "category": "huishoudelijk",
    "audience": "huishoudens die een droger willen naast of in plaats van de waslijn",
    "product_ideas": "Miele T1 Excellence, Bosch Serie 8 warmtepompdroger, AEG T8, Samsung OptimalDry, LG Dual Inverter"
  },
  {
    "slug": "beste-strijkijzer-2026",
    "topic_nl": "de beste strijkijzers en stoomgeneratoren voor kreukvrij wasgoed",
    "category": "huishoudelijk",
    "audience": "huishoudens die veel strijken en een betrouwbaar apparaat willen",
    "product_ideas": "Philips PerfectCare, Tefal Pro Express, Braun CareStyle, Bosch Sensixx, Laurastar"
  },
  {
    "slug": "beste-stofzuiger-met-zak-2026",
    "topic_nl": "de beste stofzuigers met zak: krachtig, hygiënisch en betrouwbaar",
    "category": "schoonmaken",
    "audience": "huishoudens die de voorkeur geven aan een traditionele stofzuiger met zak om hygiënische redenen of allergieën",
    "product_ideas": "Miele Complete C3, Bosch BGL8, Siemens VSQ8, Philips PowerPro Compact, AEG VX9"
  },
  {
    "slug": "beste-dweilrobot-2026",
    "topic_nl": "de beste dweilrobots en vloerreinigers voor harde vloeren",
    "category": "schoonmaken",
    "audience": "huishoudens met harde vloeren (laminaat, tegels, PVC) die dweilen willen automatiseren",
    "product_ideas": "iRobot Braava Jet, Roborock Dyad, Bissell CrossWave, Kärcher FC 7, Tineco Floor One S5"
  },
  {
    "slug": "beste-raamreiniger-2026",
    "topic_nl": "de beste elektrische raamreinigers en ramenwissers",
    "category": "schoonmaken",
    "audience": "huishoudens die ramen, douchewanden en spiegels streeploos schoon willen zonder gedoe",
    "product_ideas": "Kärcher WV 6 Plus, Leifheit Window Vac, Vileda Windomatic, Bosch GlassVAC, Kärcher WV 2"
  },
  {
    "slug": "beste-staafmixer-2026",
    "topic_nl": "de beste staafmixers voor soep, smoothies en babyvoeding",
    "category": "keuken",
    "audience": "thuiskoks die een veelzijdige staafmixer willen voor dagelijks gebruik",
    "product_ideas": "Braun MultiQuick, Philips ProMix, Bosch ErgoMixx, KitchenAid staafmixer, Tefal Optiblend"
  }
]
